gdaslib/DatabaseConnectionSettings.py
gdaslib/__init__.py
gdaslib/gdasdb.py
gdaslib/database/GamesGamesModel.py
gdaslib/database/StreamGamesModel.py
gdaslib/database/TableSentGames.py
gdaslib/database/TeamModel.py
GDASLib-0.0.1.dist-info/LICENSE
GDASLib-0.0.1.dist-info/METADATA
GDASLib-0.0.1.dist-info/WHEEL
GDASLib-0.0.1.dist-info/top_level.txt
GDASLib-0.0.1.dist-info/RECORD
